llm_bedrock_mistral.py
llm_bedrock_mistral-0.1.0.dist-info/LICENSE
llm_bedrock_mistral-0.1.0.dist-info/METADATA
llm_bedrock_mistral-0.1.0.dist-info/WHEEL
llm_bedrock_mistral-0.1.0.dist-info/entry_points.txt
llm_bedrock_mistral-0.1.0.dist-info/top_level.txt
llm_bedrock_mistral-0.1.0.dist-info/RECORD
