Metadata-Version: 2.1
Name: llm-bedrock-mistral
Version: 0.1.0
Summary: LLM plugin for Mistral on AWS Bedrock
Author: Travis Pinney
License: Apache-2.0
Project-URL: Homepage, https://github.com/tlpinney/llm-bedrock-mistral
Classifier: License :: OSI Approved :: Apache Software License
License-File: LICENSE
Requires-Dist: llm
Requires-Dist: boto3 >=1.28.85
Provides-Extra: test
Requires-Dist: pytest ; extra == 'test'
